cobratools/__init__.py
cobratools/general/__init__.py
cobratools/general/config.dist.py
cobratools/general/config.py
cobratools/general/gencode_extract.py
cobratools/general/maf2bed.py
cobratools/general/maf_coverage.py
cobratools/general/maf_filter.py
cobratools/general/maf_n_dist.py
cobratools/general/maf_sample.py
cobratools/general/maf_split.py
cobratools/general/maf_verify.py
cobratools/general/models/__init__.py
cobratools/general/models/alphabets.py
cobratools/general/models/bed.py
cobratools/general/models/btools.py
cobratools/general/models/common.py
cobratools/general/models/constants.py
cobratools/general/models/fasta.py
cobratools/general/models/filters.py
cobratools/general/models/gene.py
cobratools/general/models/gtf.py
cobratools/general/models/maf.py
cobratools/general/models/transcript.py
cobratools/general/tests/__init__.py
cobratools/general/tests/test_filter_common_gaps.py
cobratools/general/tests/test_filter_species.py
cobratools/general/tests/test_gtf.py
cobratools/rlr/__init__.py
cobratools/rlr/colors.py
cobratools/rlr/models/__init__.py
cobratools/rlr/models/merger.py
cobratools/rlr/models/rnaz.py
cobratools/rlr/plots/__init__.py
cobratools/rlr/plots/floating_bar.py
cobratools/rlr/plots/genomic_context_stacked100_exonic.py
cobratools/rlr/plots/genomic_context_stacked100_non-coding.py
cobratools/rlr/plots/length_distribution.py
cobratools/rlr/plots/mpi_distribution_histo.py
cobratools/rlr/plots/nseq_distribution_histo.py
cobratools/rlr/sandbox/__init__.py
cobratools/rlr/sandbox/count_nts.py
cobratools/rlr/sandbox/file_check.py
cobratools/rlr/sandbox/flank.py
cobratools/rlr/sandbox/human_loci.py
cobratools/rlr/sandbox/intersect_all.py
cobratools/rlr/sandbox/kill_missing_ref.py
cobratools/rlr/sandbox/locarna_check.py
cobratools/rlr/sandbox/locarna_scriptify.py
cobratools/rlr/sandbox/locarna_scriptify_merged.py
cobratools/rlr/sandbox/merge.py
cobratools/rlr/sandbox/multi_window_loci.py
cobratools/rlr/sandbox/oops.py
cobratools-0.0.2.dist-info/LICENSE.md
cobratools-0.0.2.dist-info/METADATA
cobratools-0.0.2.dist-info/WHEEL
cobratools-0.0.2.dist-info/top_level.txt
cobratools-0.0.2.dist-info/RECORD
