Metadata-Version: 2.1
Name: cobratools
Version: 0.0.2
Summary: Tools for bioinformatics and glue for RLR analysis pipeline
Home-page: https://github.com/cbcafiero/cobra
Author: Clayton Cafiero
Author-email: clayton.cafiero@uvm.edu
License: UNKNOWN
Platform: UNKNOWN
Classifier: Programming Language :: Python :: 3
Classifier: License :: OSI Approved :: GNU General Public License v3 or later (GPLv3+)
Classifier: Operating System :: OS Independent
